simple_events/__init__.py
simple_events/base_manager.py
simple_events/event_manager.py
simple_events/file_parser.py
simple_events/joy_map.py
simple_events/key_manager.py
simple_events/key_map.py
simple_events/py.typed
pygame_simple_events-1.1.1.dist-info/LICENSE
pygame_simple_events-1.1.1.dist-info/METADATA
pygame_simple_events-1.1.1.dist-info/WHEEL
pygame_simple_events-1.1.1.dist-info/top_level.txt
pygame_simple_events-1.1.1.dist-info/RECORD
