Metadata-Version: 2.1
Name: pygame_simple_events
Version: 1.1.1
Summary: A simple decorator-based event handler and key bind system for use with pygame
Author-email: BetterBuiltFool <betterbuiltfool@gmail.com>
Classifier: Programming Language :: Python :: 3
Classifier: License :: OSI Approved :: MIT License
Classifier: Operating System :: OS Independent
Classifier: Topic :: Games/Entertainment
Classifier: Topic :: Software Development :: Libraries :: pygame
Classifier: Typing :: Typed
Requires-Python: >=3.12.4
License-File: LICENSE
